setup.py
polished/__init__.py
polished/decorators.py
polished/main.py
polished.egg-info/PKG-INFO
polished.egg-info/SOURCES.txt
polished.egg-info/dependency_links.txt
polished.egg-info/entry_points.txt
polished.egg-info/requires.txt
polished.egg-info/top_level.txt
polished/backends/__init__.py
polished/backends/base.py
polished/backends/django.py
polished/backends/pelican.py
polished/backends/simple.py
polished/backends/helpers/__init__.py
polished/backends/helpers/timeout.py
polished/backends/mixins/__init__.py
polished/backends/mixins/base.py
polished/backends/mixins/driver.py
polished/backends/mixins/git.py
polished/backends/mixins/polisher.py
polished/backends/mixins/video.py
polished/tests/__init__.py