Metadata-Version: 1.1
Name: polished
Version: 0.0.5
Summary: Generates screenshots of a website based on git history
Home-page: https://github.com/ckcollab/polished
Author: Eric Carmichael
Author-email: eric@ckcollab.com
License: MIT
Keywords: link checker
Platform: UNKNOWN
Classifier: Intended Audience :: Developers
Classifier: Natural Language :: English
Classifier: License :: OSI Approved :: MIT License
Classifier: Operating System :: OS Independent
Classifier: Programming Language :: Python
Classifier: Programming Language :: Python :: 2
Classifier: Programming Language :: Python :: 2.6
Classifier: Programming Language :: Python :: 2.7
Classifier: Topic :: Software Development :: Libraries :: Python Modules
